googlesheets/__init__.py
googlesheets/gitsheets.py
googlesheets/sheets.py
googlesheets/simpsheets.py
django_google_sheets-0.1.0.dist-info/LICENCE
django_google_sheets-0.1.0.dist-info/METADATA
django_google_sheets-0.1.0.dist-info/WHEEL
django_google_sheets-0.1.0.dist-info/top_level.txt
django_google_sheets-0.1.0.dist-info/RECORD
