Metadata-Version: 2.1
Name: django-google-sheets
Version: 0.1.0
Summary: Não é oficial do google
Author: issei momonge
Author-email: mggyggf@gmail.com
License: MIT License
Keywords: django google sheets
License-File: LICENCE
Requires-Dist: gspread
Requires-Dist: django
Requires-Dist: gitpython
